[
  {
    "id": "d1",
    "name": "Брускетта с томатами и базиликом",
    "description": "Хрустящий чиабатта, сливочные томаты, свежий базилик, оливковое масло",
    "image": "/placeholders/dish-1.webp",
    "station": "cold",
    "format": [
      "furshet",
      "banket",
      "coffee-break"
    ],
    "tier": [
      "economy",
      "standard"
    ],
    "pricePerGuest": 180,
    "servingsPerGuest": 1,
    "allergens": [
      "gluten",
      "milk"
    ],
    "dietBadges": [],
    "childFriendly": true,
    "kcal": 210
  },
  {
    "id": "d2",
    "name": "Тартар из лосося с авокадо",
    "description": "Норвежский лосось, спелое авокадо, соус понзу, кунжут",
    "image": "/placeholders/dish-2.webp",
    "station": "cold",
    "format": [
      "furshet",
      "banket"
    ],
    "tier": [
      "premium",
      "luxury"
    ],
    "pricePerGuest": 420,
    "servingsPerGuest": 1,
    "allergens": [
      "fish",
      "sesame"
    ],
    "dietBadges": [],
    "childFriendly": false,
    "kcal": 290
  },
  {
    "id": "d3",
    "name": "Карпаччо из говядины",
    "description": "Тонкие слайсы говядины, руккола, пармезан, трюфельное масло",
    "image": "/placeholders/dish-3.webp",
    "station": "cold",
    "format": [
      "banket"
    ],
    "tier": [
      "premium",
      "luxury"
    ],
    "pricePerGuest": 380,
    "servingsPerGuest": 1,
    "allergens": [
      "milk"
    ],
    "dietBadges": [],
    "childFriendly": false,
    "kcal": 245
  },
  {
    "id": "d4",
    "name": "Севиче из креветок",
    "description": "Креветки, лайм, красный лук, кинза, перец чили",
    "image": "/placeholders/dish-4.webp",
    "station": "cold",
    "format": [
      "furshet",
      "banket"
    ],
    "tier": [
      "standard",
      "premium"
    ],
    "pricePerGuest": 320,
    "servingsPerGuest": 1,
    "allergens": [
      "crustaceans"
    ],
    "dietBadges": [],
    "childFriendly": false,
    "kcal": 180
  },
  {
    "id": "d5",
    "name": "Хумус с питой",
    "description": "Классический хумус, оливковое масло, паприка, тёплая пита",
    "image": "/placeholders/dish-5.webp",
    "station": "cold",
    "format": [
      "furshet",
      "coffee-break"
    ],
    "tier": [
      "economy",
      "standard"
    ],
    "pricePerGuest": 140,
    "servingsPerGuest": 1,
    "allergens": [
      "gluten",
      "sesame"
    ],
    "dietBadges": [
      "vegan"
    ],
    "childFriendly": true,
    "kcal": 310
  },
  {
    "id": "h1",
    "name": "Говядина в перечном соусе",
    "description": "Медальоны говядины, сливочно-перечный соус, запечённый картофель",
    "image": "/placeholders/dish-h1.webp",
    "station": "hot",
    "format": [
      "banket"
    ],
    "tier": [
      "standard",
      "premium"
    ],
    "pricePerGuest": 550,
    "servingsPerGuest": 1,
    "allergens": [
      "milk"
    ],
    "dietBadges": [],
    "childFriendly": false,
    "kcal": 480
  },
  {
    "id": "h2",
    "name": "Куриное филе су-вид",
    "description": "Куриная грудка су-вид, пюре из сельдерея, соус демиглас",
    "image": "/placeholders/dish-h2.webp",
    "station": "hot",
    "format": [
      "banket",
      "furshet"
    ],
    "tier": [
      "economy",
      "standard"
    ],
    "pricePerGuest": 340,
    "servingsPerGuest": 1,
    "allergens": [
      "milk",
      "celery"
    ],
    "dietBadges": [],
    "childFriendly": true,
    "kcal": 380
  },
  {
    "id": "h3",
    "name": "Лосось на гриле",
    "description": "Филе лосося, соус терияки, киноа с овощами",
    "image": "/placeholders/dish-h3.webp",
    "station": "hot",
    "format": [
      "banket"
    ],
    "tier": [
      "premium",
      "luxury"
    ],
    "pricePerGuest": 520,
    "servingsPerGuest": 1,
    "allergens": [
      "fish",
      "soy"
    ],
    "dietBadges": [],
    "childFriendly": false,
    "kcal": 420
  },
  {
    "id": "h4",
    "name": "Ризотто с белыми грибами",
    "description": "Арборио, белые грибы, пармезан, трюфельное масло",
    "image": "/placeholders/dish-h4.webp",
    "station": "hot",
    "format": [
      "banket"
    ],
    "tier": [
      "premium",
      "luxury"
    ],
    "pricePerGuest": 460,
    "servingsPerGuest": 1,
    "allergens": [
      "milk"
    ],
    "dietBadges": [
      "vegan"
    ],
    "childFriendly": true,
    "kcal": 510
  },
  {
    "id": "s1",
    "name": "Тирамису в стаканчике",
    "description": "Маскарпоне, савоярди, эспрессо, какао — порционный формат",
    "image": "/placeholders/dish-s1.webp",
    "station": "desserts",
    "format": [
      "banket",
      "furshet",
      "coffee-break"
    ],
    "tier": [
      "economy",
      "standard",
      "premium",
      "luxury"
    ],
    "pricePerGuest": 220,
    "servingsPerGuest": 1,
    "allergens": [
      "gluten",
      "eggs",
      "milk"
    ],
    "dietBadges": [],
    "childFriendly": false,
    "kcal": 340
  },
  {
    "id": "s2",
    "name": "Панна-котта с ягодным кули",
    "description": "Сливочная панна-котта, сезонные ягоды, мятный сироп",
    "image": "/placeholders/dish-s2.webp",
    "station": "desserts",
    "format": [
      "banket",
      "furshet"
    ],
    "tier": [
      "standard",
      "premium"
    ],
    "pricePerGuest": 260,
    "servingsPerGuest": 1,
    "allergens": [
      "milk"
    ],
    "dietBadges": [],
    "childFriendly": true,
    "kcal": 290
  },
  {
    "id": "s3",
    "name": "Макарон ассорти",
    "description": "Французское миндальное печенье: фисташка, малина, шоколад",
    "image": "/placeholders/dish-s3.webp",
    "station": "desserts",
    "format": [
      "furshet",
      "coffee-break"
    ],
    "tier": [
      "premium",
      "luxury"
    ],
    "pricePerGuest": 180,
    "servingsPerGuest": 2,
    "allergens": [
      "nuts",
      "eggs",
      "milk"
    ],
    "dietBadges": [
      "gluten-free"
    ],
    "childFriendly": true,
    "kcal": 160
  },
  {
    "id": "b1",
    "name": "Лимонад домашний",
    "description": "Лимон, мята, имбирь, газированная вода",
    "image": "/placeholders/dish-b1.webp",
    "station": "drinks",
    "format": [
      "furshet",
      "banket",
      "coffee-break"
    ],
    "tier": [
      "economy",
      "standard",
      "premium",
      "luxury"
    ],
    "pricePerGuest": 120,
    "servingsPerGuest": 2,
    "allergens": [],
    "dietBadges": [
      "vegan",
      "gluten-free"
    ],
    "childFriendly": true,
    "kcal": 60
  },
  {
    "id": "b2",
    "name": "Смузи-бар",
    "description": "3 вида смузи на выбор: манго-маракуйя, клубника-банан, шпинат-яблоко",
    "image": "/placeholders/dish-b2.webp",
    "station": "drinks",
    "format": [
      "coffee-break",
      "detskoe"
    ],
    "tier": [
      "standard",
      "premium"
    ],
    "pricePerGuest": 200,
    "servingsPerGuest": 1,
    "allergen": [],
    "dietBadges": [
      "vegan",
      "gluten-free"
    ],
    "childFriendly": true,
    "kcal": 150
  }
]